awdible/__init__.py
awdible/config.py
awdible/console/__init__.py
awdible/console/application.py
awdible/console/gui.py
awdible/console/run.py
awdible/core/__init__.py
awdible/core/awdible.py
awdible/core/convert.py
awdible/core/crop.py
awdible/core/defaults.py
awdible/core/io.py
awdible/core/prerequires.py
awdible/core/search.py
awdible/core/validators.py
awdible/core/video.py
awdible/gui/__init__.py
awdible/gui/front.py
awdible/helpers.py
awdible/logger.py
awdible/validators.py
awdible-0.2.5.dist-info/LICENSE
awdible-0.2.5.dist-info/METADATA
awdible-0.2.5.dist-info/WHEEL
awdible-0.2.5.dist-info/entry_points.txt
awdible-0.2.5.dist-info/RECORD
