Metadata-Version: 2.1
Name: awdible
Version: 0.2.5
Summary: Awdible - Just the best free version of audible
Home-page: https://alexandregazagnes.github.io/awdible/
License: GPL-3.0
Keywords: python,music,tool,utils,youtube
Author: AlexandreGazagnes
Author-email: alex@gazagnes.net
Maintainer: AlexandreGazagnes
Maintainer-email: alex@gazagnes.net
Requires-Python: >=3.8,<3.12.0
Classifier: Development Status :: 5 - Production/Stable
Classifier: Environment :: Other Environment
Classifier: Intended Audience :: Developers
Classifier: Intended Audience :: Education
Classifier: Intended Audience :: Information Technology
Classifier: License :: OSI Approved :: GNU General Public License v3 (GPLv3)
Classifier: Programming Language :: Python
Classifier: Programming Language :: Python :: 3
Classifier: Programming Language :: Python :: 3.8
Classifier: Programming Language :: Python :: 3.9
Classifier: Programming Language :: Python :: 3.10
Classifier: Programming Language :: Python :: 3.11
Classifier: Programming Language :: Python :: 3 :: Only
Classifier: Topic :: Software Development :: Libraries :: Python Modules
Project-URL: Changelog, https://alexandregazagnes.github.io/awdible/CHANGELOG/
Project-URL: Documentation, https://alexandregazagnes.github.io/awdible/
Project-URL: Issues, https://github.com/AlexandreGazagnes/awdible/issues
Project-URL: Repository, https://github.com/AlexandreGazagnes/awdible/tree/main
